setup.py
distributions_djl/Binomialdistribution.py
distributions_djl/Gaussiandistribution.py
distributions_djl/Generaldistribution.py
distributions_djl/__init__.py
distributions_djl.egg-info/PKG-INFO
distributions_djl.egg-info/SOURCES.txt
distributions_djl.egg-info/dependency_links.txt
distributions_djl.egg-info/not-zip-safe
distributions_djl.egg-info/top_level.txt