Metadata-Version: 1.0
Name: distributions-djl
Version: 0.1
Summary: Gaussian and Binomial distributions
Home-page: UNKNOWN
Author: Derrick Lewis
Author-email: UNKNOWN
License: UNKNOWN
Platform: UNKNOWN
